non_local_detector/__init__.py
non_local_detector/_version.py
non_local_detector/continuous_state_transitions.py
non_local_detector/core.py
non_local_detector/discrete_state_transitions.py
non_local_detector/environment.py
non_local_detector/initial_conditions.py
non_local_detector/observation_models.py
non_local_detector/types.py
non_local_detector/analysis/__init__.py
non_local_detector/analysis/distance1D.py
non_local_detector/analysis/distance2D.py
non_local_detector/analysis/posterior.py
non_local_detector/likelihoods/__init__.py
non_local_detector/likelihoods/clusterless_kde.py
non_local_detector/likelihoods/common.py
non_local_detector/likelihoods/no_spike.py
non_local_detector/likelihoods/sorted_spikes_glm.py
non_local_detector/likelihoods/sorted_spikes_kde.py
non_local_detector/model_checking/__init__.py
non_local_detector/model_checking/clusterless.py
non_local_detector/model_checking/highest_posterior_density.py
non_local_detector/model_checking/posterior_consistency.py
non_local_detector/model_checking/sorted_spikes.py
non_local_detector/models/__init__.py
non_local_detector/models/base.py
non_local_detector/models/cont_frag_model.py
non_local_detector/models/decoder.py
non_local_detector/models/multienvironment_model.py
non_local_detector/models/non_local_model.py
non_local_detector/models/nospike_cont_frag_model.py
non_local_detector/simulate/__init__.py
non_local_detector/simulate/clusterless_simulation.py
non_local_detector/simulate/simulate.py
non_local_detector/simulate/sorted_spikes_simulation.py
non_local_detector/tests/test_version_import.py
non_local_detector/visualization/__init__.py
non_local_detector/visualization/figurl_1D.py
non_local_detector/visualization/figurl_2D.py
non_local_detector/visualization/static.py
non_local_detector-0.6.9.dist-info/METADATA
non_local_detector-0.6.9.dist-info/WHEEL
non_local_detector-0.6.9.dist-info/licenses/LICENSE
non_local_detector-0.6.9.dist-info/RECORD
