Metadata-Version: 2.3
Name: non_local_detector
Version: 0.6.9
Summary: A python package to decode non-local activity from neural data
Project-URL: Homepage, https://github.com/LorenFrankLab/non_local_detector
Project-URL: Bug Tracker, https://github.com/LorenFrankLab/non_local_detector/issues
Author-email: Eric Denovellis <eric.denovellis@ucsf.edu>
License: MIT License
Classifier: License :: OSI Approved :: MIT License
Classifier: Operating System :: OS Independent
Classifier: Programming Language :: Python :: 3
Requires-Python: >=3.8
Requires-Dist: jax
Requires-Dist: jaxlib
Requires-Dist: matplotlib
Requires-Dist: networkx
Requires-Dist: numpy
Requires-Dist: pandas
Requires-Dist: patsy
Requires-Dist: scikit-learn
Requires-Dist: scipy
Requires-Dist: seaborn
Requires-Dist: tqdm
Requires-Dist: track-linearization
Requires-Dist: xarray
Provides-Extra: gpu
Requires-Dist: jax[cuda]; extra == 'gpu'
Provides-Extra: test
Requires-Dist: black; extra == 'test'
Requires-Dist: pytest; extra == 'test'
Requires-Dist: pytest-cov; extra == 'test'
Provides-Extra: viz
Requires-Dist: sortingview; extra == 'viz'
